momo.py
momo_writer-0.1.1.dist-info/METADATA
momo_writer-0.1.1.dist-info/WHEEL
momo_writer-0.1.1.dist-info/entry_points.txt
momo_writer-0.1.1.dist-info/top_level.txt
momo_writer-0.1.1.dist-info/RECORD
