Metadata-Version: 2.4
Name: momo-writer
Version: 0.1.1
Summary: 一个沉浸式的命令行小说写作工具 (A text-immersive CLI novel writing tool)
License: MIT
Classifier: Development Status :: 4 - Beta
Classifier: Environment :: Console
Classifier: Intended Audience :: End Users/Desktop
Classifier: Topic :: Text Editors :: Word Processors
Classifier: Programming Language :: Python :: 3
Classifier: Operating System :: OS Independent
Requires-Python: >=3.8
Requires-Dist: prompt_toolkit>=3.0.0
